qiskit_aws_braket_provider/__init__.py
qiskit_aws_braket_provider/awsbackend.py
qiskit_aws_braket_provider/awsjob.py
qiskit_aws_braket_provider/awsprovider.py
qiskit_aws_braket_provider/conversions_configuration.py
qiskit_aws_braket_provider/conversions_properties.py
qiskit_aws_braket_provider/transpilation.py
qiskit_aws_braket_provider-0.0.2.dist-info/LICENSE
qiskit_aws_braket_provider-0.0.2.dist-info/METADATA
qiskit_aws_braket_provider-0.0.2.dist-info/WHEEL
qiskit_aws_braket_provider-0.0.2.dist-info/top_level.txt
qiskit_aws_braket_provider-0.0.2.dist-info/RECORD
